pycontractsdk/__init__.py
pycontractsdk/contract.py
pycontractsdk-0.0.1.dist-info/METADATA
pycontractsdk-0.0.1.dist-info/RECORD
pycontractsdk-0.0.1.dist-info/WHEEL
pycontractsdk-0.0.1.dist-info/entry_points.txt
pycontractsdk-0.0.1.dist-info/top_level.txt
