Metadata-Version: 2.1
Name: pycontractsdk
Version: 0.0.1
Summary: This is a sdk of constract
Home-page: https://gitlab.hard-chain.cn/cport/pyconstractsdk
Author: yuyongpeng
Author-email: yuyongpeng@hotmail.com
License: MIT
Keywords: solidity web3 constract sdk
Platform: UNKNOWN
Classifier: Development Status :: 3 - Alpha
Classifier: Intended Audience :: Developers
Classifier: Natural Language :: English
Classifier: Topic :: Utilities
Classifier: License :: OSI Approved :: MIT License
Classifier: Programming Language :: Python :: 3.6
Classifier: Topic :: Software Development :: Libraries
Requires-Python: >=3.6
Requires-Dist: web3 (>=4.8.3)
Requires-Dist: eth-account
Requires-Dist: eth-utils
Requires-Dist: logbook
